bertdistiller/__init__.py
bertdistiller/data/__init__.py
bertdistiller/data/dataset.py
bertdistiller/distillation/__init__.py
bertdistiller/distillation/minilm/__init__.py
bertdistiller/distillation/minilm/args.py
bertdistiller/distillation/minilm/modeling.py
bertdistiller/distillation/minilm/trainer.py
bertdistiller/evaluation/__init__.py
bertdistiller/evaluation/evaluation.py
bertdistiller/evaluation/run_glue.py
bertdistiller-0.1.2.dist-info/LICENSE
bertdistiller-0.1.2.dist-info/METADATA
bertdistiller-0.1.2.dist-info/WHEEL
bertdistiller-0.1.2.dist-info/RECORD
