Metadata-Version: 2.1
Name: bertdistiller
Version: 0.1.2
Summary: BERT Distillation
Home-page: https://github.com/milistu/bertdistiller
License: Apache-2.0
Keywords: BERT,Distillation,PyTorch,Transformer Networks,NLP
Author: milistu
Author-email: studen.m98@gmail.com
Requires-Python: >=3.10,<=3.12
Classifier: Intended Audience :: Science/Research
Classifier: License :: OSI Approved :: Apache Software License
Classifier: Programming Language :: Python :: 3
Classifier: Programming Language :: Python :: 3.10
Classifier: Programming Language :: Python :: 3.11
Classifier: Programming Language :: Python :: 3.12
Classifier: Topic :: Scientific/Engineering :: Artificial Intelligence
Requires-Dist: datasets (>=3.2.0,<4.0.0)
Requires-Dist: evaluate (>=0.4.3,<0.5.0)
Requires-Dist: loguru (>=0.7.3,<0.8.0)
Requires-Dist: scikit-learn (>=1.6.1,<2.0.0)
Requires-Dist: scipy (>=1.15.2,<2.0.0)
Requires-Dist: transformers[torch] (>=4.49.0,<5.0.0)
Project-URL: Repository, https://github.com/milistu/bertdistiller
